example/example.py
panel_print/__init__.py
panel_print-0.1.3.dist-info/METADATA
panel_print-0.1.3.dist-info/WHEEL
panel_print-0.1.3.dist-info/top_level.txt
panel_print-0.1.3.dist-info/RECORD
