Metadata-Version: 2.4
Name: panel-print
Version: 0.1.3
Summary: A Python library that provides beautiful console output using Rich panels for enhanced debugging and data visualization.
Author-email: Haotian Deng <haotiandeng@stu.sufe.edu.cn>
Requires-Python: >=3.10
Requires-Dist: itables>=2.5.2
Requires-Dist: rich>=14.1.0
